Workbook

Sheet Cover
B3: AlphaEdge — Pre-Seed Investment Model
B4: Institutional-Grade Market Intelligence · 45 Emerging Markets · DCC-GARCH Correlation Engine
B5: PRIVATE & CONFIDENTIAL — FRIENDS & FAMILY ROUND — Q2 2026
B8: Round Size | D8: Valuation Cap | F8: Instrument | H8: Min. Ticket
B9: ₹35 Lakhs | D9: ₹3.5 Cr | F9: SAFE / CCD | H9: ₹1 Lakh
B10: Friends & Family Pre-Seed | D10: Pre-Money Implied | F10: Converts at Seed Round | H10: Flexible for Close Circle
B12: MODEL CONTENTS
B13: Assumptions | C13: All model inputs — valuation cap, growth rates, dilution, USD/INR rate
B14: Returns Summary | C14: Investment amount vs. return multiples at 1Y / 3Y / 5Y across 3 scenarios
B15: Valuation Journey | C15: Pre-Seed → Seed → Series A → Exit milestones with implied valuations
B16: Revenue Model | C16: Subscriber growth, MRR → ARR → implied company valuation by year
B17: Equity & Dilution | C17: Ownership table by ticket size through all funding rounds
B25: DISCLAIMER: This model is for informational purposes only and is not an offer or solicitation to buy or sell securities. Investment in early-stage ventures carries significant risk, including total loss of capital. All projections are estimates based on stated assumptions and do not guarantee future returns. Recipients should seek independent professional advice before making any investment decision. AlphaEdge Ventures · April 2026 · Confidential.

Sheet Assumptions
B2: ALPHAEDGE — MODEL ASSUMPTIONS
B3: Blue = Input cells you can change | All other cells are formulas | C3: ● Hardcoded inputs | D3: ● Formula / calculated | E3: ● Linked from another sheet
B5: A. PRE-SEED ROUND DETAILS
B6: Round Size (₹ Lakhs) | C6: 35 | E6: Friends & Family raise — Q2 2026
B7: Pre-Money Valuation Cap (₹ Cr) | C7: 3.5 | E7: SAFE / CCD converts at seed at this cap
B8: Min. Ticket Size (₹ Lakhs) | C8: 1 | E8: Flexible for close circle
B9: Instrument | C9: SAFE / CCD | E9: Converts at next priced round
B10: USD/INR Rate | C10: 94 | E10: Source: Xe.com, April 2026
B11: Total Pre-Seed Equity Pool (%) | C11: =C6/C7 -> 10 | E11: Auto-calculated from round size / valuation cap
B13: B. PHASE 2 SEED ROUND (Formal Raise — $12M Target)
B14: Phase 2 Seed Raise (USD M) | C14: 12 | E14: Source: AlphaEdge investor materials, 2026
B15: Seed Pre-Money Valuation (USD M) | C15: 40 | E15: $40M pre / $52M post (₹376 Cr / ₹489 Cr)
B16: Seed Post-Money Valuation (₹ Cr) | C16: =(C14+C15)*C10/10000000 -> 0.0004888 | E16: Phase 2 raise + pre-money × USD/INR rate
B17: Seed Dilution to Pre-Seed Investors (%) | C17: 0.23 | E17: New shares issued to seed investors — typical ~20-25%
B19: C. SERIES A ASSUMPTIONS
B20: Series A Dilution (%) | C20: 0.2 | E20: Typical institutional Series A dilution
B22: D. SCENARIO VALUATIONS (for Exit Value Calculation)
B23: Scenario Parameter | C23: Conservative | D23: Base Case | E23: Bull Case
B24: 1Y — Mark-to-Market Valuation (₹ Cr) | C24: 300 | D24: 489 | E24: 750 | F24: Post-seed mark. Base = $52M post-money converted to INR
B25: 3Y — Series A / Growth Valuation (₹ Cr) | C25: 1000 | D25: 2500 | E25: 5000 | F25: Revenue-based multiple. Base ~ 50x ARR at $10K MRR trajectory
B26: 5Y — Pre-IPO / Exit Valuation (₹ Cr) | C26: 3000 | D26: 8000 | E26: 20000 | F26: Comparable: Zerodha ₹36K Cr, Groww ₹23K Cr, niche EM SaaS at 10-20x
B27: Revenue Multiple Assumed (x ARR) | C27: 15 | D27: 30 | E27: 60 | F27: Conservative = mature SaaS; Bull = Bloomberg-comparable moat
B29: E. REVENUE MODEL INPUTS
B30: Target Subscribers at Launch (Paid) | C30: 50 | E30: 10-12 weeks post-seed. Source: Investor materials
B31: Monthly Price per Subscriber (₹) | C31: 2499 | E31: ₹2,499/month. = ~$199/month. vs Bloomberg ₹25L/year
B32: Monthly Subscriber Growth Rate — Conservative (%) | C32: 0.1 | E32: 10% MoM net adds
B33: Monthly Subscriber Growth Rate — Base (%) | C33: 0.2 | E33: 20% MoM net adds
B34: Monthly Subscriber Growth Rate — Bull (%) | C34: 0.35 | E34: 35% MoM net adds — strong Discord channel pull
B35: Target MRR (USD) to Trigger Seed | C35: 10000 | E35: Source: AlphaEdge Phase 2 milestones — $10K MRR

Sheet Returns Summary
B2: ALPHAEDGE — PRE-SEED RETURNS SUMMARY
B3: Investment Amount vs. Projected Returns at 1 Year / 3 Years / 5 Years · Pre-Money Cap: ₹3.5 Cr · Instrument: SAFE/CCD · Round: ₹35 Lakhs
B4: All inputs pulled from Assumptions sheet. Change inputs there — this table recalculates automatically.
B6: INVESTMENT | E6: ◀ 1 YEAR RETURNS (Post-Seed Mark-to-Market) ▶ | K6: ◀ 3 YEAR RETURNS (Series A Growth Stage) ▶ | Q6: ◀ 5 YEAR RETURNS (Pre-IPO / Exit Scenario) ▶
B7: Ticket (₹ Lakhs) | C7: Initial Equity % | D7: Post-Dilution Equity % | E7: 🐻 Conservative Return Value (₹ Cr) | F7: 🐻 Conservative Multiple | G7: 📊 Base Case Return Value (₹ Cr) | H7: 📊 Base Case Multiple | I7: 🚀 Bull Case Return Value (₹ Cr) | J7: 🚀 Bull Case Multiple | K7: 🐻 Conservative Return Value (₹ Cr) | L7: 🐻 Conservative Multiple | M7: 📊 Base Case Return Value (₹ Cr) | N7: 📊 Base Case Multiple | O7: 🚀 Bull Case Return Value (₹ Cr) | P7: 🚀 Bull Case Multiple | Q7: 🐻 Conservative Return Value (₹ Cr) | R7: 🐻 Conservative Multiple | S7: 📊 Base Case Return Value (₹ Cr) | T7: 📊 Base Case Multiple | U7: 🚀 Bull Case Return Value (₹ Cr) | V7: 🚀 Bull Case Multiple
E8: Conservative (Multiple) | F8: Base (Multiple) | G8: Bull (Multiple) | H8: Conservative (Multiple) | I8: Base (Multiple) | J8: Bull (Multiple) | K8: Conservative (Multiple) | L8: Base (Multiple) | M8: Bull (Multiple)
B9: 1 | C9: =B9/(Assumptions!C7*100) -> 0.0028571429 | D9: =C9*(1-Assumptions!C17)*(1-Assumptions!C20) -> 0.00176 | E9: =D9*Assumptions!C24 -> 0.528 | F9: =IF(B9=0,0,E9/(B9/100)) -> 52.8 | G9: =D9*Assumptions!D24 -> 0.86064 | H9: =IF(B9=0,0,G9/(B9/100)) -> 86.064 | I9: =D9*Assumptions!E24 -> 1.32 | J9: =IF(B9=0,0,I9/(B9/100)) -> 132 | K9: =D9*Assumptions!C25 -> 1.76 | L9: =IF(B9=0,0,K9/(B9/100)) -> 176 | M9: =D9*Assumptions!D25 -> 4.4 | N9: =IF(B9=0,0,M9/(B9/100)) -> 440 | O9: =D9*Assumptions!E25 -> 8.8 | P9: =IF(B9=0,0,O9/(B9/100)) -> 880 | Q9: =D9*Assumptions!C26 -> 5.28 | R9: =IF(B9=0,0,Q9/(B9/100)) -> 528 | S9: =D9*Assumptions!D26 -> 14.08 | T9: =IF(B9=0,0,S9/(B9/100)) -> 1408 | U9: =D9*Assumptions!E26 -> 35.2 | V9: =IF(B9=0,0,U9/(B9/100)) -> 3520
B10: 2 | C10: =B10/(Assumptions!C7*100) -> 0.0057142857 | D10: =C10*(1-Assumptions!C17)*(1-Assumptions!C20) -> 0.00352 | E10: =D10*Assumptions!C24 -> 1.056 | F10: =IF(B10=0,0,E10/(B10/100)) -> 52.8 | G10: =D10*Assumptions!D24 -> 1.72128 | H10: =IF(B10=0,0,G10/(B10/100)) -> 86.064 | I10: =D10*Assumptions!E24 -> 2.64 | J10: =IF(B10=0,0,I10/(B10/100)) -> 132 | K10: =D10*Assumptions!C25 -> 3.52 | L10: =IF(B10=0,0,K10/(B10/100)) -> 176 | M10: =D10*Assumptions!D25 -> 8.8 | N10: =IF(B10=0,0,M10/(B10/100)) -> 440 | O10: =D10*Assumptions!E25 -> 17.6 | P10: =IF(B10=0,0,O10/(B10/100)) -> 880 | Q10: =D10*Assumptions!C26 -> 10.56 | R10: =IF(B10=0,0,Q10/(B10/100)) -> 528 | S10: =D10*Assumptions!D26 -> 28.16 | T10: =IF(B10=0,0,S10/(B10/100)) -> 1408 | U10: =D10*Assumptions!E26 -> 70.4 | V10: =IF(B10=0,0,U10/(B10/100)) -> 3520
B11: 5 | C11: =B11/(Assumptions!C7*100) -> 0.014285714 | D11: =C11*(1-Assumptions!C17)*(1-Assumptions!C20) -> 0.0088 | E11: =D11*Assumptions!C24 -> 2.64 | F11: =IF(B11=0,0,E11/(B11/100)) -> 52.8 | G11: =D11*Assumptions!D24 -> 4.3032 | H11: =IF(B11=0,0,G11/(B11/100)) -> 86.064 | I11: =D11*Assumptions!E24 -> 6.6 | J11: =IF(B11=0,0,I11/(B11/100)) -> 132 | K11: =D11*Assumptions!C25 -> 8.8 | L11: =IF(B11=0,0,K11/(B11/100)) -> 176 | M11: =D11*Assumptions!D25 -> 22 | N11: =IF(B11=0,0,M11/(B11/100)) -> 440 | O11: =D11*Assumptions!E25 -> 44 | P11: =IF(B11=0,0,O11/(B11/100)) -> 880 | Q11: =D11*Assumptions!C26 -> 26.4 | R11: =IF(B11=0,0,Q11/(B11/100)) -> 528 | S11: =D11*Assumptions!D26 -> 70.4 | T11: =IF(B11=0,0,S11/(B11/100)) -> 1408 | U11: =D11*Assumptions!E26 -> 176 | V11: =IF(B11=0,0,U11/(B11/100)) -> 3520
B12: 10 | C12: =B12/(Assumptions!C7*100) -> 0.028571429 | D12: =C12*(1-Assumptions!C17)*(1-Assumptions!C20) -> 0.0176 | E12: =D12*Assumptions!C24 -> 5.28 | F12: =IF(B12=0,0,E12/(B12/100)) -> 52.8 | G12: =D12*Assumptions!D24 -> 8.6064 | H12: =IF(B12=0,0,G12/(B12/100)) -> 86.064 | I12: =D12*Assumptions!E24 -> 13.2 | J12: =IF(B12=0,0,I12/(B12/100)) -> 132 | K12: =D12*Assumptions!C25 -> 17.6 | L12: =IF(B12=0,0,K12/(B12/100)) -> 176 | M12: =D12*Assumptions!D25 -> 44 | N12: =IF(B12=0,0,M12/(B12/100)) -> 440 | O12: =D12*Assumptions!E25 -> 88 | P12: =IF(B12=0,0,O12/(B12/100)) -> 880 | Q12: =D12*Assumptions!C26 -> 52.8 | R12: =IF(B12=0,0,Q12/(B12/100)) -> 528 | S12: =D12*Assumptions!D26 -> 140.8 | T12: =IF(B12=0,0,S12/(B12/100)) -> 1408 | U12: =D12*Assumptions!E26 -> 352 | V12: =IF(B12=0,0,U12/(B12/100)) -> 3520
B13: 25 | C13: =B13/(Assumptions!C7*100) -> 0.071428571 | D13: =C13*(1-Assumptions!C17)*(1-Assumptions!C20) -> 0.044 | E13: =D13*Assumptions!C24 -> 13.2 | F13: =IF(B13=0,0,E13/(B13/100)) -> 52.8 | G13: =D13*Assumptions!D24 -> 21.516 | H13: =IF(B13=0,0,G13/(B13/100)) -> 86.064 | I13: =D13*Assumptions!E24 -> 33 | J13: =IF(B13=0,0,I13/(B13/100)) -> 132 | K13: =D13*Assumptions!C25 -> 44 | L13: =IF(B13=0,0,K13/(B13/100)) -> 176 | M13: =D13*Assumptions!D25 -> 110 | N13: =IF(B13=0,0,M13/(B13/100)) -> 440 | O13: =D13*Assumptions!E25 -> 220 | P13: =IF(B13=0,0,O13/(B13/100)) -> 880 | Q13: =D13*Assumptions!C26 -> 132 | R13: =IF(B13=0,0,Q13/(B13/100)) -> 528 | S13: =D13*Assumptions!D26 -> 352 | T13: =IF(B13=0,0,S13/(B13/100)) -> 1408 | U13: =D13*Assumptions!E26 -> 880 | V13: =IF(B13=0,0,U13/(B13/100)) -> 3520
B14: 35 | C14: =B14/(Assumptions!C7*100) -> 0.1 | D14: =C14*(1-Assumptions!C17)*(1-Assumptions!C20) -> 0.0616 | E14: =D14*Assumptions!C24 -> 18.48 | F14: =IF(B14=0,0,E14/(B14/100)) -> 52.8 | G14: =D14*Assumptions!D24 -> 30.1224 | H14: =IF(B14=0,0,G14/(B14/100)) -> 86.064 | I14: =D14*Assumptions!E24 -> 46.2 | J14: =IF(B14=0,0,I14/(B14/100)) -> 132 | K14: =D14*Assumptions!C25 -> 61.6 | L14: =IF(B14=0,0,K14/(B14/100)) -> 176 | M14: =D14*Assumptions!D25 -> 154 | N14: =IF(B14=0,0,M14/(B14/100)) -> 440 | O14: =D14*Assumptions!E25 -> 308 | P14: =IF(B14=0,0,O14/(B14/100)) -> 880 | Q14: =D14*Assumptions!C26 -> 184.8 | R14: =IF(B14=0,0,Q14/(B14/100)) -> 528 | S14: =D14*Assumptions!D26 -> 492.8 | T14: =IF(B14=0,0,S14/(B14/100)) -> 1408 | U14: =D14*Assumptions!E26 -> 1232 | V14: =IF(B14=0,0,U14/(B14/100)) -> 3520
B16: NOTES: Returns shown as ₹ Crore value at exit and Return Multiple (×). Post-Dilution Equity = Pre-Seed % × (1 − Seed Dilution 23%) × (1 − Series A Dilution 20%). Conservative = Measured growth; Base = $52M seed valuation → ₹489 Cr; Bull = Strong EM SaaS traction. All figures are projections — not guarantees.

Sheet Valuation Journey
B2: ALPHAEDGE — FUNDING ROUND & VALUATION JOURNEY
B4: Stage | C4: Timeline | D4: Raise Amount | E4: Pre-Money | F4: Post-Money | G4: Key Milestone / Trigger
B5: Pre-Seed | C5: Q2 2026 (Now) | D5: ₹35 Lakhs | E5: ₹3.5 Cr | F5: ₹3.5 Cr + ₹35L = ~₹3.85 Cr | G5: F&F round closes. Product completion funded. SAFE issued.
B6: Phase 2 — Seed | C6: Q3–Q4 2026 (~6 months) | D6: $150K–200K (₹1.4–1.9 Cr) | E6: ~₹10 Cr implied | F6: ~₹11.5 Cr | G6: Beta launch. $10K MRR milestone. 50 paid subscribers.
B7: Formal Seed | C7: Q1 2027 (~12 months) | D7: $12M (₹112.8 Cr) | E7: $40M (₹376 Cr) | F7: $52M (₹489 Cr) | G7: DCC-GARCH live. News Intelligence live. AlphaCopy live. $10K MRR proven.
B8: Series A | C8: 2028–2029 (~3 years) | D8: $30–50M | E8: ₹1,000–2,500 Cr (Conservative–Base) | F8: ₹1,300–3,000 Cr | G8: Pan-EM expansion. 5,000+ subscribers. $1M+ ARR. Institutional clients.
B9: Pre-IPO / Exit | C9: 2030–2031 (~5 years) | D9: IPO / Strategic | E9: ₹3,000–20,000 Cr | F9: — | G9: India-first EM intelligence platform. Bloomberg alternative for 45 markets.
B11: PRE-SEED INVESTOR DILUTION SCHEDULE
B12: Metric | C12: At Pre-Seed | D12: After Phase 2 Seed | E12: After Formal Seed ($12M) | F12: After Series A | G12: At Exit
B13: Example: ₹10L Ticket | C13: 2.857% | D13: 2.857% | E13: 2.20% | F13: 1.76% | G13: 1.76% of exit value
B14: Round Dilution | C14: — | D14: ~3% (Phase 2) | E14: ~23% (Formal Seed) | F14: ~20% (Series A) | G14: Cumulative ~40%
B15: Dilution Factor | C15: 1.000× | D15: 0.970× | E15: 0.770× | F15: 0.800× | G15: 0.597×
B16: Retained Eq. Factor | C16: 100% | D16: 97.0% | E16: 74.7% | F16: 59.7% | G16: 59.7% of original
B17: Base Case Return (₹ Cr) for ₹10L invested | C17: — | D17: ~0.22 Cr mark | E17: ~0.87 Cr (1Y) | F17: ~4.42 Cr (3Y) | G17: ~11.15 Cr (5Y)

Sheet Revenue Model
B2: ALPHAEDGE — REVENUE MODEL (SUBSCRIBER → ARR → VALUATION)
B4: Metric | C4: M1 | D4: M2 | E4: M3 | F4: M4 | G4: M5 | H4: M6 | I4: M7 | J4: M8 | K4: M9 | L4: M10 | M4: M11 | N4: M12 | O4: Year 1 | P4: Year 2 | Q4: Year 3
B5: 🐻 CONSERVATIVE SCENARIO
B6: Paid Subscribers | C6: =Assumptions!C30*(1+Assumptions!C32) -> 55 | D6: =C6*(1+Assumptions!C32) -> 60.5 | E6: =D6*(1+Assumptions!C32) -> 66.55 | F6: =E6*(1+Assumptions!C32) -> 73.205 | G6: =F6*(1+Assumptions!C32) -> 80.5255 | H6: =G6*(1+Assumptions!C32) -> 88.57805 | I6: =H6*(1+Assumptions!C32) -> 97.435855 | J6: =I6*(1+Assumptions!C32) -> 107.17944 | K6: =J6*(1+Assumptions!C32) -> 117.89738 | L6: =K6*(1+Assumptions!C32) -> 129.68712 | M6: =L6*(1+Assumptions!C32) -> 142.65584 | N6: =M6*(1+Assumptions!C32) -> 156.92142 | O6: =N6 -> 156.92142 | P6: =N6*(1+Assumptions!C32)^(1*12) -> 492.48663 | Q6: =N6*(1+Assumptions!C32)^(2*12) -> 1545.634
B7: MRR (₹ Lakhs) | C7: =C6*Assumptions!C31/100000 -> 1.37445 | D7: =D6*Assumptions!C31/100000 -> 1.511895 | E7: =E6*Assumptions!C31/100000 -> 1.6630845 | F7: =F6*Assumptions!C31/100000 -> 1.8293929 | G7: =G6*Assumptions!C31/100000 -> 2.0123322 | H7: =H6*Assumptions!C31/100000 -> 2.2135655 | I7: =I6*Assumptions!C31/100000 -> 2.434922 | J7: =J6*Assumptions!C31/100000 -> 2.6784142 | K7: =K6*Assumptions!C31/100000 -> 2.9462556 | L7: =L6*Assumptions!C31/100000 -> 3.2408812 | M7: =M6*Assumptions!C31/100000 -> 3.5649693 | N7: =N6*Assumptions!C31/100000 -> 3.9214663 | O7: =O6*Assumptions!C31/100000 -> 3.9214663 | P7: =P6*Assumptions!C31/100000 -> 12.307241 | Q7: =Q6*Assumptions!C31/100000 -> 38.625394
B8: ARR (₹ Lakhs) | C8: =C7*12 -> 16.4934 | D8: =D7*12 -> 18.14274 | E8: =E7*12 -> 19.957014 | F8: =F7*12 -> 21.952715 | G8: =G7*12 -> 24.147987 | H8: =H7*12 -> 26.562786 | I8: =I7*12 -> 29.219064 | J8: =J7*12 -> 32.140971 | ... Q8: =Q7*12 -> 463.50473
B9: Implied Valuation (₹ Cr) | C9: =C8*Assumptions!C27/100 -> 2.47401 | D9: =D8*Assumptions!C27/100 -> 2.721411 | E9: =E8*Assumptions!C27/100 -> 2.9935521 | F9: =F8*Assumptions!C27/100 -> 3.2929073 | G9: =G8*Assumptions!C27/100 -> 3.622198 | H9: =H8*Assumptions!C27/100 -> 3.9844178 | I9: =I8*Assumptions!C27/100 -> 4.3828596 | J9: =J8*Assumptions!C27/100 -> 4.8211456 | K9: =K8*Assumptions!C27/100 -> 5.3032602 | L9: =L8*Assumptions!C27/100 -> 5.8335862 | M9: =M8*Assumptions!C27/100 -> 6.4169448 | N9: =N8*Assumptions!C27/100 -> 7.0586393 | O9: =O8*Assumptions!C27/100 -> 7.0586393 | P9: =P8*Assumptions!C27/100 -> 22.153034 | Q9: =Q8*Assumptions!C27/100 -> 69.52571
B15: 📊 BASE CASE SCENARIO
B16: Paid Subscribers | C16: =Assumptions!C30*(1+Assumptions!C33) -> 60 | D16: =C16*(1+Assumptions!C33) -> 72 | E16: =D16*(1+Assumptions!C33) -> 86.4 | F16: =E16*(1+Assumptions!C33) -> 103.68 | G16: =F16*(1+Assumptions!C33) -> 124.416 | H16: =G16*(1+Assumptions!C33) -> 149.2992 | I16: =H16*(1+Assumptions!C33) -> 179.15904 | J16: =I16*(1+Assumptions!C33) -> 214.99085 | K16: =J16*(1+Assumptions!C33) -> 257.98902 | L16: =K16*(1+Assumptions!C33) -> 309.58682 | M16: =L16*(1+Assumptions!C33) -> 371.50419 | N16: =M16*(1+Assumptions!C33) -> 445.80502 | O16: =N16 -> 445.80502 | P16: =N16*(1+Assumptions!C33)^(1*12) -> 3974.8424 | Q16: =N16*(1+Assumptions!C33)^(2*12) -> 35440.094
B17: MRR (₹ Lakhs) | C17: =C16*Assumptions!C31/100000 -> 1.4994 | D17: =D16*Assumptions!C31/100000 -> 1.79928 | E17: =E16*Assumptions!C31/100000 -> 2.159136 | F17: =F16*Assumptions!C31/100000 -> 2.5909632 | G17: =G16*Assumptions!C31/100000 -> 3.1091558 | H17: =H16*Assumptions!C31/100000 -> 3.730987 | I17: =I16*Assumptions!C31/100000 -> 4.4771844 | J17: =J16*Assumptions!C31/100000 -> 5.3726213 | K17: =K16*Assumptions!C31/100000 -> 6.4471455 | L17: =L16*Assumptions!C31/100000 -> 7.7365747 | M17: =M16*Assumptions!C31/100000 -> 9.2838896 | N17: =N16*Assumptions!C31/100000 -> 11.140668 | O17: =O16*Assumptions!C31/100000 -> 11.140668 | P17: =P16*Assumptions!C31/100000 -> 99.331311 | Q17: =Q16*Assumptions!C31/100000 -> 885.64794
B18: ARR (₹ Lakhs) | C18: =C17*12 -> 17.9928 | D18: =D17*12 -> 21.59136 | E18: =E17*12 -> 25.909632 | F18: =F17*12 -> 31.091558 | G18: =G17*12 -> 37.30987 | H18: =H17*12 -> 44.771844 | I18: =I17*12 -> 53.726213 | J18: =J17*12 -> 64.471455 | ... Q18: =Q17*12 -> 10627.775
B19: Implied Valuation (₹ Cr) | C19: =C18*Assumptions!D27/100 -> 5.39784 | D19: =D18*Assumptions!D27/100 -> 6.477408 | E19: =E18*Assumptions!D27/100 -> 7.7728896 | F19: =F18*Assumptions!D27/100 -> 9.3274675 | G19: =G18*Assumptions!D27/100 -> 11.192961 | H19: =H18*Assumptions!D27/100 -> 13.431553 | I19: =I18*Assumptions!D27/100 -> 16.117864 | J19: =J18*Assumptions!D27/100 -> 19.341437 | K19: =K18*Assumptions!D27/100 -> 23.209724 | L19: =L18*Assumptions!D27/100 -> 27.851669 | M19: =M18*Assumptions!D27/100 -> 33.422003 | N19: =N18*Assumptions!D27/100 -> 40.106403 | O19: =O18*Assumptions!D27/100 -> 40.106403 | P19: =P18*Assumptions!D27/100 -> 357.59272 | Q19: =Q18*Assumptions!D27/100 -> 3188.3326
B25: 🚀 BULL CASE SCENARIO
B26: Paid Subscribers | C26: =Assumptions!C30*(1+Assumptions!C34) -> 67.5 | D26: =C26*(1+Assumptions!C34) -> 91.125 | E26: =D26*(1+Assumptions!C34) -> 123.01875 | F26: =E26*(1+Assumptions!C34) -> 166.07531 | G26: =F26*(1+Assumptions!C34) -> 224.20167 | H26: =G26*(1+Assumptions!C34) -> 302.67226 | I26: =H26*(1+Assumptions!C34) -> 408.60755 | J26: =I26*(1+Assumptions!C34) -> 551.62019 | K26: =J26*(1+Assumptions!C34) -> 744.68725 | L26: =K26*(1+Assumptions!C34) -> 1005.3278 | M26: =L26*(1+Assumptions!C34) -> 1357.1925 | N26: =M26*(1+Assumptions!C34) -> 1832.2099 | O26: =N26 -> 1832.2099 | P26: =N26*(1+Assumptions!C34)^(1*12) -> 67139.863 | Q26: =N26*(1+Assumptions!C34)^(2*12) -> 2460286.4
B27: MRR (₹ Lakhs) | C27: =C26*Assumptions!C31/100000 -> 1.686825 | D27: =D26*Assumptions!C31/100000 -> 2.2772138 | E27: =E26*Assumptions!C31/100000 -> 3.0742386 | F27: =F26*Assumptions!C31/100000 -> 4.1502221 | G27: =G26*Assumptions!C31/100000 -> 5.6027998 | H27: =H26*Assumptions!C31/100000 -> 7.5637797 | I27: =I26*Assumptions!C31/100000 -> 10.211103 | J27: =J26*Assumptions!C31/100000 -> 13.784989 | K27: =K26*Assumptions!C31/100000 -> 18.609734 | L27: =L26*Assumptions!C31/100000 -> 25.123142 | M27: =M26*Assumptions!C31/100000 -> 33.916241 | N27: =N26*Assumptions!C31/100000 -> 45.786925 | O27: =O26*Assumptions!C31/100000 -> 45.786925 | P27: =P26*Assumptions!C31/100000 -> 1677.8252 | Q27: =Q26*Assumptions!C31/100000 -> 61482.558
B28: ARR (₹ Lakhs) | C28: =C27*12 -> 20.2419 | D28: =D27*12 -> 27.326565 | E28: =E27*12 -> 36.890863 | F28: =F27*12 -> 49.802665 | G28: =G27*12 -> 67.233597 | H28: =H27*12 -> 90.765356 | I28: =I27*12 -> 122.53323 | J28: =J27*12 -> 165.41986 | ... Q28: =Q27*12 -> 737790.69
B29: Implied Valuation (₹ Cr) | C29: =C28*Assumptions!E27/100 -> 12.14514 | D29: =D28*Assumptions!E27/100 -> 16.395939 | E29: =E28*Assumptions!E27/100 -> 22.134518 | F29: =F28*Assumptions!E27/100 -> 29.881599 | G29: =G28*Assumptions!E27/100 -> 40.340158 | H29: =H28*Assumptions!E27/100 -> 54.459214 | I29: =I28*Assumptions!E27/100 -> 73.519939 | J29: =J28*Assumptions!E27/100 -> 99.251917 | K29: =K28*Assumptions!E27/100 -> 133.99009 | L29: =L28*Assumptions!E27/100 -> 180.88662 | M29: =M28*Assumptions!E27/100 -> 244.19694 | N29: =N28*Assumptions!E27/100 -> 329.66586 | O29: =O28*Assumptions!E27/100 -> 329.66586 | P29: =P28*Assumptions!E27/100 -> 12080.341 | Q29: =Q28*Assumptions!E27/100 -> 442674.42

Sheet Equity & Dilution
B2: ALPHAEDGE — EQUITY OWNERSHIP & DILUTION BY TICKET SIZE
B4: Ticket (₹ L) | C4: Equity at Pre-Seed Cap | D4: After Phase 2 Seed (~3% dil.) | E4: After Formal Seed (~23% dil.) | F4: After Series A (~20% dil.) | G4: Cumulative Dilution | H4: Retained Equity (Final)
B5: 1 | C5: =B5/(Assumptions!C7*100) -> 0.0028571429 | D5: =C5*(1-0.03) -> 0.0027714286 | E5: =D5*(1-Assumptions!C17) -> 0.002134 | F5: =E5*(1-Assumptions!C20) -> 0.0017072 | G5: =1-(F5/C5) -> 0.40248 | H5: =F5 -> 0.0017072
B6: 2 | C6: =B6/(Assumptions!C7*100) -> 0.0057142857 | D6: =C6*(1-0.03) -> 0.0055428571 | E6: =D6*(1-Assumptions!C17) -> 0.004268 | F6: =E6*(1-Assumptions!C20) -> 0.0034144 | G6: =1-(F6/C6) -> 0.40248 | H6: =F6 -> 0.0034144
B7: 5 | C7: =B7/(Assumptions!C7*100) -> 0.014285714 | D7: =C7*(1-0.03) -> 0.013857143 | E7: =D7*(1-Assumptions!C17) -> 0.01067 | F7: =E7*(1-Assumptions!C20) -> 0.008536 | G7: =1-(F7/C7) -> 0.40248 | H7: =F7 -> 0.008536
B8: 10 | C8: =B8/(Assumptions!C7*100) -> 0.028571429 | D8: =C8*(1-0.03) -> 0.027714286 | E8: =D8*(1-Assumptions!C17) -> 0.02134 | F8: =E8*(1-Assumptions!C20) -> 0.017072 | G8: =1-(F8/C8) -> 0.40248 | H8: =F8 -> 0.017072
B9: 25 | C9: =B9/(Assumptions!C7*100) -> 0.071428571 | D9: =C9*(1-0.03) -> 0.069285714 | E9: =D9*(1-Assumptions!C17) -> 0.05335 | F9: =E9*(1-Assumptions!C20) -> 0.04268 | G9: =1-(F9/C9) -> 0.40248 | H9: =F9 -> 0.04268
B10: 35 | C10: =B10/(Assumptions!C7*100) -> 0.1 | D10: =C10*(1-0.03) -> 0.097 | E10: =D10*(1-Assumptions!C17) -> 0.07469 | F10: =E10*(1-Assumptions!C20) -> 0.059752 | G10: =1-(F10/C10) -> 0.40248 | H10: =F10 -> 0.059752
B12: DILUTION SEQUENCE: Pre-Seed (SAFE/CCD) → Phase 2 Seed (₹1.4–1.9 Cr raise, ~3% dilution) → Formal Seed ($12M raise, ~23% new shares issued) → Series A (~20% new shares). Dilution percentages are estimates; actual depends on round valuation at time of raise. SAFE/CCD converts at the better of pre-money cap or priced round discount.
